saves/__init__.py
saves/saves.py
saves-0.1.dist-info/LICENSE
saves-0.1.dist-info/METADATA
saves-0.1.dist-info/WHEEL
saves-0.1.dist-info/top_level.txt
saves-0.1.dist-info/RECORD
