Metadata-Version: 2.1
Name: saves
Version: 0.1
Summary: simple data persistence package.
Home-page: https://github.com/Akirakong/saves
Author: UNKNOWN
Author-email: UNKNOWN
License: MIT
Keywords: Persistence sqlite3 data
Platform: UNKNOWN
